pjplan/__init__.py
pjplan/calendar.py
pjplan/resource.py
pjplan/schedule.py
pjplan/task.py
pjplan/utils.py
pjplan/wbs.py
pjplan/alg/__init__.py
pjplan/alg/critical_path.py
pjplan/io/__init__.py
pjplan/io/csv_io.py
pjplan/io/raw.py
pjplan/viz/__init__.py
pjplan/viz/dhtmlx/__init__.py
pjplan/viz/dhtmlx/gantt.py
pjplan/viz/dhtmlx/templates/gantt.html
pjplan/viz/dhtmlx/templates/resource_usage.html
pjplan/viz/mermaid/__init__.py
pjplan/viz/mermaid/gantt.py
pjplan/viz/mermaid/network.py
pjplan/viz/mermaid/templates/gantt.html
pjplan/viz/mermaid/templates/network.html
pjplan-0.0.14.dist-info/METADATA
pjplan-0.0.14.dist-info/WHEEL
pjplan-0.0.14.dist-info/licenses/LICENSE
pjplan-0.0.14.dist-info/RECORD
