Metadata-Version: 2.4
Name: pjplan
Version: 0.0.14
Summary: Python library for plan projects
Project-URL: Homepage, https://github.com/artem-snopkov/pjplan
Project-URL: Bug Tracker, https://github.com/artem-snopkov/pjplan/issues
Author-email: Artem Snopkov <artem.snopkov@gmail.com>
License-File: LICENSE
Classifier: License :: OSI Approved :: MIT License
Classifier: Operating System :: OS Independent
Classifier: Programming Language :: Python :: 3
Requires-Python: >=3.7
